ai_cli/__init__.py
ai_cli/__main__.py
ai_cli/ai_cli.py
python_ai_cli-0.0.17.dist-info/METADATA
python_ai_cli-0.0.17.dist-info/WHEEL
python_ai_cli-0.0.17.dist-info/entry_points.txt
python_ai_cli-0.0.17.dist-info/top_level.txt
python_ai_cli-0.0.17.dist-info/RECORD
