Metadata-Version: 2.4
Name: python-ai-cli
Version: 0.0.17
Summary: AI CLI
Author-email: Marc Nuri <marc@marcnuri.com>
License-Expression: Apache-2.0
Project-URL: Homepage, https://github.com/manusa/ai-cli
Project-URL: Repository, https://github.com/manusa/ai-cli
Classifier: Programming Language :: Python :: 3
Classifier: Operating System :: OS Independent
Requires-Python: >=3.6
